{
  "stdout_truncated": false,
  "stdout": "INFO: [EDA] eda: version 0.5.1\nINFO: [EDA] main: eda sim --no-color --tool verilator --seed=1 --verilate-args=-Wno-fatal --waves bench_riscv_core; (run from /app/eda.work/f3129156-7264-4853-83f3-e6af5c52ad87.edacmd)\nINFO: [EDA] python: version 3.12.12\nINFO: [EDA] eda from: /app/venv/lib/python3.12/site-packages/opencos\nINFO: [EDA] eda_config: using config: /app/venv/lib/python3.12/site-packages/opencos/eda_config_defaults.yml\nINFO: [EDA] *** OpenCOS EDA ***\nINFO: [EDA] Auto tool setup for command: sim\nINFO: [EDA] --Detected tool--   --Path--                    --Version--  \nINFO: [EDA] verilator           (/usr/local/bin/verilator)  5.042        \nINFO: [EDA] --Detected other--  --Path--                    --Version--  \nINFO: [EDA] docker              /usr/bin/docker             29.1.3       \nINFO: [EDA] sim: top-most target name: bench_riscv_core (./DEPS.yml::bench_riscv_core::line=71)\nINFO: [EDA] artifacts: add_extension \"fst\", search paths: eda.work/bench_riscv_core.sim\nINFO: [EDA] artifacts: add_extension \"vcd\", search paths: eda.work/bench_riscv_core.sim\nINFO: [EDA] exec: /usr/local/bin/verilator --binary -Wno-CASEINCOMPLETE -Wno-REALCVT -Wno-SELRANGE -Wno-TIMESCALEMOD -Wno-UNSIGNED -Wno-WIDTH -Wno-fatal --timing --assert --autoflush -sv -CFLAGS -O1 -j 1 --trace-structs --trace-params --trace-fst -top tb_riscv_core -o sim.exe +define+SIMULATION=1 /app/eda.work/f3129156-7264-4853-83f3-e6af5c52ad87.edacmd/alu_32bit.sv /app/eda.work/f3129156-7264-4853-83f3-e6af5c52ad87.edacmd/alu_8bit.sv /app/eda.work/f3129156-7264-4853-83f3-e6af5c52ad87.edacmd/mac_unit.sv /app/eda.work/f3129156-7264-4853-83f3-e6af5c52ad87.edacmd/alu_mac_datapath.sv /app/eda.work/f3129156-7264-4853-83f3-e6af5c52ad87.edacmd/riscv_decoder.sv /app/eda.work/f3129156-7264-4853-83f3-e6af5c52ad87.edacmd/register_file.sv /app/eda.work/f3129156-7264-4853-83f3-e6af5c52ad87.edacmd/execute_stage.sv /app/eda.work/f3129156-7264-4853-83f3-e6af5c52ad87.edacmd/fetch_stage.sv /app/eda.work/f3129156-7264-4853-83f3-e6af5c52ad87.edacmd/writeback_stage.sv /app/eda.work/f3129156-7264-4853-83f3-e6af5c52ad87.edacmd/hazard_unit.sv /app/eda.work/f3129156-7264-4853-83f3-e6af5c52ad87.edacmd/riscv_core.sv /app/eda.work/f3129156-7264-4853-83f3-e6af5c52ad87.edacmd/tb_riscv_core.sv (in eda.work/bench_riscv_core.sim, tee_fpath='compile.log')\nINFO: [EDA] PID 30401 for /usr/local/bin/verilator\n%Error-PINNOTFOUND: /app/eda.work/f3129156-7264-4853-83f3-e6af5c52ad87.edacmd/riscv_core.sv:86:10: Pin not found: 'rd2'\n                                                                                                 : ... Suggested alternative: 'rs2'\n   86 |         .rd2         (wb_rd_hi),\n      |          ^~~\n                    ... For error description see https://verilator.org/warn/PINNOTFOUND?v=5.042\n%Error-PINNOTFOUND: /app/eda.work/f3129156-7264-4853-83f3-e6af5c52ad87.edacmd/riscv_core.sv:87:10: Pin not found: 'write_data2'\n                                                                                                 : ... Suggested alternative: 'write_data'\n   87 |         .write_data2 (wb_data_hi),\n      |          ^~~~~~~~~~~\n%Error-PINNOTFOUND: /app/eda.work/f3129156-7264-4853-83f3-e6af5c52ad87.edacmd/riscv_core.sv:88:10: Pin not found: 'reg_write2'\n                                                                                                 : ... Suggested alternative: 'reg_write'\n   88 |         .reg_write2  (wb_en_hi)\n      |          ^~~~~~~~~~\n%Error: Exiting due to 3 error(s)\nINFO: [EDA] subprocess_run_background: wrote: /app/eda.work/f3129156-7264-4853-83f3-e6af5c52ad87.edacmd/eda.work/bench_riscv_core.sim/compile.log\nINFO: [EDA] exec: returned with error (return code: 1)\nERROR: [EDA] Tool - verilator, total counts: 0 tool warnings, 4 tool errors\nERROR: [EDA] sim - verilator - tb_riscv_core: exec returned with error code: 1\nINFO: [EDA] Wrote artifacts JSON: eda.work/bench_riscv_core.sim/artifacts.json\nINFO: [EDA]   --> eda.work/eda.log  (text)\nINFO: [EDA]   --> eda.work/bench_riscv_core.sim/eda_output_config.yml  (yaml)\nINFO: [EDA]   --> eda.work/bench_riscv_core.sim/compile.log  (text)\nINFO: [EDA]   --> eda.work/bench_riscv_core.sim/eda.errors.log  (text)\nINFO: [EDA]   --> eda.work/bench_riscv_core.sim/eda_errors.json  (json)\nINFO: [EDA] Exiting with 0 warnings, 2 errors\nINFO: [EDA] Closing logfile: eda.work/eda.log\n",
  "stdout_size": 4344,
  "stdout_total_size": 4344,
  "message": "Simulation failed with return code 255",
  "warnings": 0,
  "errors": 0,
  "stderr": "",
  "return_code": 255,
  "start_time": 1776603193.1300986,
  "stop_time": 1776603193.8902855,
  "waves_returned": false,
  "wave_file": null,
  "wave_file_size": null,
  "verilator_version": null,
  "system_info": null,
  "work_dir_files": null,
  "frogger_status_reason": "Simulation failed with return code 255",
  "fst_s3_key": null,
  "fst_s3_bucket": null,
  "error": "Simulation failed with return code 255"
}